obsolete_cryptography/__init__.py
obsolete_cryptography/mhash.cpython-39-x86_64-linux-gnu.so
obsolete_cryptography/mcrypt.cpython-39-x86_64-linux-gnu.so
obsolete_cryptography-0.2.1.dist-info/LICENSE.md
obsolete_cryptography-0.2.1.dist-info/WHEEL
obsolete_cryptography-0.2.1.dist-info/METADATA
obsolete_cryptography-0.2.1.dist-info/RECORD
