Metadata-Version: 2.1
Name: obsolete-cryptography
Version: 0.2.1
Summary: Toolbox for exploring various obsolete ciphers and hash algorithms. Based on mcrypt and mhash.
Author: dogtopus
License: ### GNU LESSER GENERAL PUBLIC LICENSE
Classifier: Development Status :: 3 - Alpha
Classifier: Programming Language :: C
Classifier: Programming Language :: Cython
Classifier: Topic :: Security :: Cryptography
Classifier: Topic :: Software Development :: Libraries :: Python Modules
Project-URL: Repository, https://github.com/dogtopus/obsolete-cryptography
Requires-Python: >=3.8
